ff_logger/__init__.py
ff_logger/base.py
ff_logger/console.py
ff_logger/database.py
ff_logger/file.py
ff_logger/json_logger.py
ff_logger/null.py
ff_logger/py.typed
ff_logger/utils.py
ff_logger-0.4.2.dist-info/licenses/LICENSE
ff_logger-0.4.2.dist-info/METADATA
ff_logger-0.4.2.dist-info/WHEEL
ff_logger-0.4.2.dist-info/top_level.txt
ff_logger-0.4.2.dist-info/RECORD
