Metadata-Version: 2.4
Name: ff-logger
Version: 0.4.2
Summary: Fenixflow structured logging package with scoped, instance-based loggers
Author-email: Ben Moag <dev@fenixflow.com>
Maintainer-email: Fenixflow Team <dev@fenixflow.com>
License: MIT
Project-URL: Homepage, https://fenixflow.com
Project-URL: Repository, https://gitlab.com/fenixflow/fenix-packages
Project-URL: Documentation, https://gitlab.com/fenixflow/fenix-packages/-/tree/main/ff-logger
Project-URL: Bug Tracker, https://gitlab.com/fenixflow/fenix-packages/-/issues
Project-URL: Changelog, https://gitlab.com/fenixflow/fenix-packages/-/blob/main/ff-logger/CHANGELOG.md
Keywords: logging,structured-logging,json-logging,scoped-logger,instance-logger,fenixflow
Classifier: Development Status :: 4 - Beta
Classifier: Intended Audience :: Developers
Classifier: License :: OSI Approved :: MIT License
Classifier: Operating System :: OS Independent
Classifier: Programming Language :: Python
Classifier: Programming Language :: Python :: 3
Classifier: Programming Language :: Python :: 3.10
Classifier: Programming Language :: Python :: 3.11
Classifier: Programming Language :: Python :: 3.12
Classifier: Topic :: Software Development :: Libraries :: Python Modules
Classifier: Topic :: System :: Logging
Classifier: Typing :: Typed
Requires-Python: >=3.10
License-File: LICENSE
Provides-Extra: dev
Requires-Dist: pytest>=7.4; extra == "dev"
Requires-Dist: pytest-asyncio>=0.21; extra == "dev"
Requires-Dist: black>=23.0; extra == "dev"
Requires-Dist: ruff>=0.1; extra == "dev"
Requires-Dist: mypy>=1.0; extra == "dev"
Provides-Extra: database
Requires-Dist: psycopg2-binary>=2.9; extra == "database"
Requires-Dist: pymysql>=1.1; extra == "database"
Dynamic: license-file
